pytodocadet.py
pytodocadet-0.0.1.dist-info/LICENSE.txt
pytodocadet-0.0.1.dist-info/METADATA
pytodocadet-0.0.1.dist-info/WHEEL
pytodocadet-0.0.1.dist-info/top_level.txt
pytodocadet-0.0.1.dist-info/RECORD
