Metadata-Version: 2.1
Name: pytodocadet
Version: 0.0.1
Summary: Simple and robust "ToDo Application" with Drag-Drop functionality.
Home-page: https://github.com/emrex32/pytodo-cadet
Author: Halil Emre Cadet
Author-email: halilemrecadet@gmail.com
License: MIT
Keywords: core package
Platform: UNKNOWN
Classifier: Development Status :: 5 - Production/Stable
Classifier: License :: OSI Approved :: MIT License
Classifier: Programming Language :: Python :: 3
Classifier: Operating System :: OS Independent
Requires-Dist: PyQt5
